.gitignore
MANIFEST.in
README.rst
setup.cfg
setup.py
docs/HISTORY.txt
docs/LICENSE.GPL
docs/LICENSE.txt
docs/MANUAL.txt
raptus/__init__.py
raptus.article.collections.egg-info/PKG-INFO
raptus.article.collections.egg-info/SOURCES.txt
raptus.article.collections.egg-info/dependency_links.txt
raptus.article.collections.egg-info/entry_points.txt
raptus.article.collections.egg-info/namespace_packages.txt
raptus.article.collections.egg-info/not-zip-safe
raptus.article.collections.egg-info/requires.txt
raptus.article.collections.egg-info/top_level.txt
raptus/article/__init__.py
raptus/article/collections/__init__.py
raptus/article/collections/collections.py
raptus/article/collections/configure.zcml
raptus/article/collections/extender.py
raptus/article/collections/interfaces.py
raptus/article/collections/browser/__init__.py
raptus/article/collections/browser/collections.gif
raptus/article/collections/browser/collections.pt
raptus/article/collections/browser/collections.py
raptus/article/collections/browser/collections_columns.gif
raptus/article/collections/browser/collections_left.gif
raptus/article/collections/browser/collections_right.gif
raptus/article/collections/browser/configure.zcml
raptus/article/collections/profiles/default/cssregistry.xml
raptus/article/collections/profiles/default/metadata.xml
raptus/article/collections/profiles/default/propertiestool.xml
raptus/article/collections/profiles/default/skins.xml
raptus/article/collections/profiles/default/types.xml
raptus/article/collections/profiles/default/viewlets.xml
raptus/article/collections/profiles/default/types/Article.xml
raptus/article/collections/skins/raptus_article_collections/raptus.article.collections.css.dtml