Metadata-Version: 1.1
Name: raptus.article.collections
Version: 1.0a2
Summary: Provides components rendering the results of contained collections
Home-page: https://github.com/Raptus/raptus.article.collections
Author: Raptus AG
Author-email: dev@raptus.com
License: GPL
Platform: UNKNOWN
Classifier: Programming Language :: Python
Classifier: Topic :: Software Development :: Libraries :: Python Modules
